boundednumbers/__init__.py
boundednumbers/bounded.py
boundednumbers/functions.py
boundednumbers/modulo_float.py
boundednumbers/modulo_int.py
boundednumbers/np_functions.py
boundednumbers/types.py
boundednumbers/unit_float.py
boundednumbers-0.1.3.dist-info/licenses/LICENSE
boundednumbers-0.1.3.dist-info/METADATA
boundednumbers-0.1.3.dist-info/WHEEL
boundednumbers-0.1.3.dist-info/top_level.txt
boundednumbers-0.1.3.dist-info/RECORD
