Metadata-Version: 2.4
Name: boundednumbers
Version: 0.1.3
Summary: Numeric helpers that keep values within explicit bounds
Author: Bounded Numbers Contributors
License: MIT License
Project-URL: Homepage, https://example.com/boundednumbers
Keywords: math,bounds,utility
Classifier: Programming Language :: Python :: 3
Classifier: License :: OSI Approved :: MIT License
Classifier: Programming Language :: Python :: 3 :: Only
Requires-Python: >=3.10
License-File: LICENSE
Dynamic: license-file
